yapl_py/__init__.py
yapl_py/regexes.py
yapl_py/renderer.py
yapl_py/utils.py
yapl_py/yapl.py
yapl_py-0.1.0.dist-info/METADATA
yapl_py-0.1.0.dist-info/WHEEL
yapl_py-0.1.0.dist-info/top_level.txt
yapl_py-0.1.0.dist-info/RECORD
