Metadata-Version: 2.4
Name: yapl-py
Version: 0.1.0
Summary: Python port of YAPL (Yet Another Prompt Language) renderer.
Author: YAPL Authors
Keywords: yapl,prompt,templating,llm,renderer
Classifier: Programming Language :: Python :: 3
Classifier: Programming Language :: Python :: 3 :: Only
Classifier: Programming Language :: Python :: 3.8
Classifier: Programming Language :: Python :: 3.9
Classifier: Programming Language :: Python :: 3.10
Classifier: Programming Language :: Python :: 3.11
Classifier: Programming Language :: Python :: 3.12
Classifier: Intended Audience :: Developers
Classifier: Topic :: Software Development :: Libraries :: Python Modules
Classifier: Typing :: Typed
Requires-Python: >=3.8
